ckanext_vip_portal-0.3.0-py3.9-nspkg.pth
ckanext/vip_portal/__init__.py
ckanext/vip_portal/config.py
ckanext/vip_portal/config_declaration.yaml
ckanext/vip_portal/interfaces.py
ckanext/vip_portal/plugin.py
ckanext/vip_portal/utils.py
ckanext/vip_portal/assets/script.js
ckanext/vip_portal/assets/style.css
ckanext/vip_portal/assets/webassets.yml
ckanext/vip_portal/tests/__init__.py
ckanext/vip_portal/tests/test_plugin.py
ckanext_vip_portal-0.3.0.dist-info/LICENSE
ckanext_vip_portal-0.3.0.dist-info/METADATA
ckanext_vip_portal-0.3.0.dist-info/WHEEL
ckanext_vip_portal-0.3.0.dist-info/entry_points.txt
ckanext_vip_portal-0.3.0.dist-info/namespace_packages.txt
ckanext_vip_portal-0.3.0.dist-info/top_level.txt
ckanext_vip_portal-0.3.0.dist-info/RECORD
